{"exclusion": [0], "al": [0, 3, 5, 6, 9, 10, 12, 13, 14, 16], "bulbar region": [0, 4], "normal limits": [0, 4], "upper motor neuron degeneration": [0, 4], "special reflexes": [0, 4], "normal expectations": [0, 4], "suspected als": [0], "surface electrode": [0, 4], "emg": [0, 14], "definite als": [0, 4], "physical exam": [0, 4], "vertical columns": [0, 4], "electrical impulses": [0, 4], "normal": [0], "el escorial": [0, 4], "diagnosing als": [0], "hoffman": [0], "abnormal": [0], "upper extremities": [0, 4], "specific information": [0, 4], "myasthenia gravis": [0, 4], "potential conditions": [0, 4], "ncv/emg": [0], "mri": [0], "genetic tests": [0, 4], "lumbar": [0], "hyperactive reflexes": [0, 4], "lmn": [0, 14, 16], "urine tests": [0, 4], "fast electrical signals": [0, 4], "extensive diagnostic": [0, 4], "als-mimic": [0], "certain time": [0, 4], "brisk/hyperactive reflexes": [0, 4], "rn": [0], "umn": [0, 14, 16], "possible diagnosis": [0, 4], "physical neurological exam": [0, 4], "electromyography": [0, 14], "diagnosis": [0, 6, 14], "potential causes": [0, 4], "catastrophic diagnosis": [0, 4], "ncv": [0, 14], "el escorial criteria": [0, 4], "spontaneous bursts": [0, 4], "evoked potentials": [0], "test": [0], "differential diagnosis and/or": [0, 4], "load google translate": [0, 1, 2, 3, 4, 5, 6, 7, 8, 9, 10, 11, 12, 13, 14, 15, 16, 17], "diagnostic criteria": [0, 4, 16], "thin needle electrode": [0, 4], "good idea": [0, 4], "ct": [0], "important part": [0, 4], "neurogenic changes": [0, 4], "awaji criteria": [0, 4], "decrease": [0], "various muscles": [0, 4], "muscle weakness": [0, 4], "trunk muscles": [0, 4], "particular symptoms": [0, 4], "google": [0, 16], "patient's": [0], "repetitive nerve stimulation": [0, 4], "different procedure": [0, 4], "alswiki": [0, 1, 2, 3, 4, 5, 6, 7, 8, 9, 10, 11, 12, 13, 14, 15, 16, 17], "insertional activity": [0, 4], "nerve conduction velocity": [0, 4], "full spine": [0, 4], "degeneration": [0], "three-part test": [0, 4], "nerve stimulation": [0, 4], "jaw jerk": [0, 4], "muscle biopsy": [0, 4], "static sounds": [0, 4], "norm": [0], "progressive": [0], "nerve signals": [0, 4], "muscle atrophy": [0, 4], "sign": [0], "surface": [0], "+1": [0], "horizontal line": [0, 4], "pet": [0], "small electric charges": [0, 4], "babinski": [0], "lower motor neuron degeneration": [0], "motor neuron degeneration": [0, 4], "electrical activity": [0, 4, 14], "differential diagnosis": [0, 4], "patient's symptoms": [0], "criterion": [0], "whole": [1], "digestive issues": [1, 4], "liquid hope": [1, 4, 15], "pal": [1, 5, 6, 9, 12, 13, 14, 15], "nutrition": [1], "farm": [1], "enteral formulas": [1, 4], "peg": [1, 14], "digestive problems": [1, 4], "healthier options": [1, 4], "complete nutrition": [1, 4], "kate": [1], "blend": [1, 15], "basic adult": [1, 4], "started": [2], "rachel": [3], "shine": [3], "hope loves": [3], "disease progresses": [3, 4], "jodi o-donnell-ames": [3, 4], "walk": [3], "entire family": [3, 4], "great importance": [3, 4], "blog post": [3, 4], "brandy lay": [3], "penguin": [3], "jennifer silverman": [3, 4], "appropriate words": [3, 4], "willing caregivers": [3, 4], "hlc": [3], "learn": [3], "special relationship": [3, 4], "tina singer-ames": [3, 4], "*": [3], "eloise lovelace": [3, 4], "wonderful organization": [3, 4], "jodi o'donnell-ames": [3, 4], "care packages": [3, 4], "your ema loves": [3], "dad": [3], "behavioral regions": [4, 14], "respiratory distress": [4, 5, 16], "handicap accessible van": [4, 9], "esclerosis lateral amiotr\u00f3fica": [4, 14], "noninvasive adapters": [4, 14], "inaccurate expectations": [4, 16], "mda loaner closet": [4, 9], "neurologist hello": [4, 10], "medical necessity": [4, 15], "diagnostic value": [4, 14], "patient 's body": [4], "turning cranks": [4, 9], "different price points": [4, 9], "uncontrolled manner": [4, 8], "lmn dominant": [4, 16], "severe side": [4, 12], "motor neuron diseases": [4, 16], "cold medicines": [4, 12], "primary lateral sclerosis": [4, 16], "forces air": [4, 9], "motor neuron death": [4, 12], "central nervous system": [4, 14], "light device": [4, 14], "positive airway pressure": [4], "oxygen generator": [4, 9, 14], "deep inhalation": [4, 14], "simple way": [4, 16], "nerve root": [4, 16], "patient 's symptoms": [4], "nerve conduction": [4, 14], "weight loss": [4, 15], "mutual journey": [4, 6], "row row row row row row": [4, 7], "motor neurons work": [4], "total volume": [4, 14], "standard car loan": [4, 9], "terminology elaboration": [4, 16], "main reason": [4, 16], "invasive ventilation": [4, 14], "carbon dioxide": [4, 14], "bowel issues": [4, 12], "pulse oximeter": [4, 14], "6k members": [4, 6], "mg-60 minute infusion": [4, 12], "reactive form": [4, 14], "mechanical ventilation": [4, 14], "early stages": [4, 9], "bed sores": [4, 9], "various neurological": [4, 14], "broad range": [4, 6], "nerve impulses": [4, 14], "o2/oxygen therapy": [4, 5], "skin changes": [4, 13], "brand pills": [4, 12], "philips respironics": [4, 9, 14], "emotion control regions": [4, 14], "long tube": [4, 14], "neuron disease": [4, 14, 16], "inappropriate times": [4, 12], "pressure measurements": [4, 14], "progressive neurological diseases": [4, 16], "hand-held shower head": [4, 9], "rough washcloth": [4, 13], "false diagnosis": [4, 10], "expiratory pressures": [4, 9, 14], "cerebrospinal fluid surrounds": [4, 14], "exfoliation tool": [4, 13], "important information": [4, 14], "exfoliate wet skin": [4], "motor neuron disease": [4, 16], "~ $": [4, 9], "sample page": [4, 7], "extra work/force": [4, 14], "destroymotor neurons": [4, 16], "progressive bulbar": [4, 16], "manual wheelchair": [4, 9], "air cushion": [4, 9], "years provokes": [4, 16], "person refers": [4, 16], "surgical procedure": [4, 14], "own mix": [4, 12], "power swallow": [4, 8], "upset stomach": [4, 12], "umn dominant": [4, 16], "power wheelchair": [4, 9], "frontotemporal dementia": [4, 14], "adjustable beds": [4, 9], "seat elevator": [4, 9], "als therapy": [4, 14], "pulse ox": [4, 14], "different diseases": [4, 16], "standard wheelchair seat": [4, 9], "discount card": [4, 12], "popular facebook": [4, 6], "direct words": [4, 16], "sarah roscenzwig": [4, 6], "routine blood tests": [4, 12], "hot water": [4, 13], "noninvasive users": [4, 9], "experience improvement": [4, 12], "spinal tap": [4, 14], "excess glutamate": [4, 12], "multiple people": [4, 14], "percussion vest": [4, 9], "nasal cannula": [4, 5], "major benefit": [4, 9], "nerve damage": [4, 14], "simplify things": [4, 16], "dosage level": [4, 12], "tight-knit group": [4, 6], "dry foods": [4, 8], "\u2019 s": [4, 12], "doctor 's office": [4], "upper motor neurons": [4, 14], "basic power wheelchair": [4, 9], "neuromuscular junction": [4, 14], "different models": [4, 9], "couple others fall": [4, 15], "json dict alswiki github io/wiki/index json": [4], "vascular endotherial growth factor": [4, 13], "false hope": [4, 16], "quantitative measure": [4, 14], "support groups": [4, 6], "operational modes": [4, 9], "motor neuron": [4, 16], "specific features": [4, 9], "lumbar vertebrae": [4, 14], "als ftd": [4, 14], "neurotrophic factors": [4, 13], "own statements": [4, 16], "assess liver function": [4, 12], "general tips": [4, 13], "medicare pay": [4], "various treatments": [4, 16], "als tdi": [4, 14], "weak arms": [4, 9], "versatile ventilator": [4, 14], "fals familial": [4, 14], "skin condition": [4, 13], "zip code area": [4, 15], "nasal canula": [4, 5], "venous catheter": [4, 12], "terms excludes": [4, 16], "information minimal filters": [4, 6], "ages 1-17+": [4, 16], "amyotrophic lateral": [4, 14], "amyotrophic lateral sclerosis": [4, 14, 16], "serious disease": [4, 16], "spinal column": [4, 14, 16], "utmost importance": [4, 5], "air hunger": [4, 5], "kugelberg-welander disease": [4, 16], "bathing/other adaptive": [4, 9], "actual name": [4, 14], "extra effort": [4, 8], "temporal lobes": [4, 14], "fals cases": [4, 14], "mental alertness": [4, 15], "motor cortex": [4, 14], "recent studies": [4, 12], "speech therapist": [4, 8], "lung function": [4, 14], "arterial blood": [4, 14], "liquids roll": [4, 8], "thick lotion": [4, 13], "arterial blood gas": [4, 5], "occupational therapist": [4, 14], "subsequent cycles": [4, 12], "spinal nerve root": [4, 16], "specialty formula": [4, 15], "oxygen therapy": [4, 5], "potential reflux": [4, 8], "list": [4], "continuous flow": [4, 14], "classical symptoms": [4, 10], "multifunction ventilator": [4, 9, 14], "actual diagnosis": [4, 16], "blood tricks": [4, 5], "internal rechargeable batteries": [4, 9], "remote control": [4, 9], "ineffective air exchange": [4, 5], "bath brush": [4, 13], "increase stomach": [4, 12], "common misconception": [4, 16], "als patient": [4, 6], "noninvasive ventilation": [4, 14], "mg-60 minute infusions": [4, 12], "specific joint": [4, 14], "interstate highway": [4, 16], "blood pressure": [4, 5], "'s disease": [4, 10], "mask interface": [4, 14], "medical interventions": [4, 16], "physical therapist": [4, 14], "bullet point": [4, 7], "clinical trials": [4, 12], "fluids and/or medications": [4, 14], "pressure support": [4], "als support": [4, 6], "liability scale": [4, 14], "therapeutic dose": [4, 12], "financial burden": [4, 12], "highway exit": [4, 16], "patient 's blood": [4], "large wheels": [4, 9], "warm water": [4, 13], "als/mnd terminology": [4, 14], "dry skin": [4, 13], "neuron dominant als": [4, 16], "hospital bed": [4, 9], "strange tastes": [4, 12], "electrical signal": [4, 16], "portable option": [4, 9], "infusion center": [4, 12], "surgical hole": [4, 14], "life/hospice care": [4, 5], "special parts": [4, 9], "quinine component": [4, 12], "experience extreme dry skin": [4, 13], "patient 's": [4], "tonic water": [4, 12], "share experiences": [4, 16], "respiratory therapist": [4, 14], "motor neuron development": [4, 16], "muscle fibers": [4, 14], "dead skin cells": [4, 13], "entire bed": [4, 9], "spinal cord": [4, 14, 16], "destroys superoxide": [4, 14], "medical devices/equipment": [4, 9], "7k members": [4], "trach tube": [4, 14], "sepsis/septic shock": [4, 15], "book library": [4, 11], "select certain options": [4, 9], "short questionnaire": [4, 14], "need": [4], "normal lifespan": [4, 16], "cites abnormalities": [4, 13], "muscle cramps": [4, 12], "versatile ventilators": [4, 9], "affects males": [4, 16], "muscle symptoms": [4, 12], "plastic tube": [4, 14], "health provider": [4, 12], "time frame": [4, 12], "transport wheelchair": [4, 9], "ample time": [4, 13], "noun": [4], "special attention": [4, 5], "and/or respiratory track": [4, 9], "manual wheelchairs": [4, 9], "liver damage": [4, 12], "blood test": [4, 5, 14], "lumbar puncture": [4, 14], "neuron diseases": [4, 16], "insulin-like growth factor-1": [4, 13], "motor nerves": [4, 14], "hard time": [4, 8], "trials underway": [4, 12], "previous dose": [4, 12], "load google": [4], "recent information": [4, 6], "hcpcs b4149": [4, 15], "regular wheelchair": [4, 9], "different motor neuron disease": [4, 16], "facebook als": [4, 6], "book qualifies": [4, 11], "continuous positive airway pressure": [4, 14], "development institute": [4, 14], "team gleason": [4, 9], "caregiver 's": [4], "tracheotomy tube": [4, 14], "suction machine": [4, 9, 14], "residual food": [4, 8], "lymes disease": [4, 10], "specific set": [4, 16], "werdnig-hoffman disease": [4, 16], "appropriate administration": [4, 5], "elderly people": [4, 9], "body part": [4, 14], "print materials": [4, 11], "functional status": [4, 14], "shower chair": [4, 9], "pressure sores": [4, 9], "mind 's": [4, 16], "u k": [4, 16], "custom power wheelchair": [4, 9], "prolong life": [4, 12], "muscular atrophy": [4], "oxygen saturation": [4, 14], "small areas": [4, 13], "skin problems": [4, 13], "specific findings": [4, 14], "abdominal wall": [4, 14], "enteral formula provider": [4, 15], "common power wheelchair brands": [4, 9], "neurotrophic factor": [4, 13], "pharmaceutical company": [4, 12], "notable folks": [4, 16], "corticospinal tracts": [4, 16], "pumice stone": [4, 13], "medical records": [4, 15], "oscillates air": [4, 9], "small sip": [4, 8], "therapeutic levels": [4, 12], "gentle movements/stretches": [4, 14], "hospital settings": [4, 5], "ages 30+": [4, 16], "total paralysis": [4, 9], "plastic bath pouf": [4, 13], "endoscopic gastrostomy": [4, 14], "inappropriate actions": [4, 16], "motor neurons": [4, 16], "potential problems": [4, 5], "cals": [5, 6, 14], "putting": [5], "astral": [5, 9, 14], "trilogy": [5, 9, 14], "never": [5, 9, 13, 14], "fatigue": [5], "inability": [5], "co2": [5, 14], "bipap": [5, 9, 14], "tachypnea": [5], "headache": [5], "o2": [5, 14], "increased": [5], "pulseox": [5], "dyspnea": [5], "comfort": [5], "dizziness": [5], "facebook": [6], "17 7k members": [6], "caregiver": [6, 14], "focus": [6, 8], "highly": [6], "pals only": [6], "info": [6], "diverse": [6], "emotional": [6], "suggestion": [6, 8, 13], "daily living": [6], "subsection": [7], "page": [7], "column": [7], "advice": [8], "dysphagia": [8], "sit": [8], "simplythick": [8], "eliminate": [8], "tuck": [8], "custom": [9], "walkers/rollators": [9], "mda": [9], "cpap": [9, 14], "ventec": [9, 14], "permobil": [9], "hoveround": [9], "bilevel positive airway pressure": [9, 14], "one": [9], "vocsn": [9, 14], "caregiver's": [9], "shower": [9], "loaner": [9], "medicare": [9, 15], "hoyer": [9], "closet": [9], "insurance": [9], "manual": [9], "jay": [9], "do not let insurance or medicare pay for": [9], "wheelchair": [9], "dme": [9], "face mask": [9], "jazzy": [9], "electromed": [9], "device": [9], "before": [9], "coughassist": [9], "acquisition": [9], "system": [9, 14], "bed": [9], "credit": [9], "digital": [9], "twin/twinxl": [9], "smartvest": [9], "hoyer lift": [9], "resmed": [9, 14], "niv": [9, 14], "roho": [9], "respironics": [9], "quantum": [9], "2019 https": [10], "lyme": [10], "disease": [10, 16], "md": [10], "reference": [10, 14], "neuroborreliosis a condition": [10], "wirsching": [10], "germany": [10], "please": [10], "borrelia": [10], "free": [11], "recording": [11], "congress": [11], "your als": [11], "file": [11], "* *": [12], "note": [12, 14], "catheter": [12], "alternative": [12], "iv": [12, 14], "part": [12], "nuedexta": [12], "avanir": [12], "zanaflex": [12], "initial": [12], "peripherally inserted": [12], "read": [12], "port": [12], "flexoril": [12], "radicava": [12], "pba": [12, 14], "riluzole": [12], "baclofen": [12], "picc": [12], "doctor's office": [12], "cvc": [12], "medication": [12], "aka": [12], "igf-": [13], "hydrocortisone": [13], "nt-3": [13], "not": [13, 14, 16], "consult": [13], "vegf": [13], "exfoliate wet skin only": [13], "eczema": [13], "apply": [13], "lotion": [13], "skin": [13], "cntf": [13], "usa": [14], "roscenzwig": [14], "terms": [14], "motor": [14, 16], "sod1": [14], "abg": [14], "cal": [14], "upper": [14, 16], "cns": [14], "button": [14], "sarah": [14], "pt": [14], "bipaps": [14], "csf": [14], "pals/pals": [14], "fvc": [14], "ot": [14], "forced": [14], "lower": [14, 16], "o2 sat": [14], "and": [14], "ftd": [14], "mnd": [14, 16], "person/people": [14], "clarification": [14], "alsa": [14], "rom": [14], "superoxide": [14], "vals/vals": [14], "pseudobulbar affect": [14], "cns-ls": [14], "ventilator": [14], "sclerosis": [14], "capacity": [14], "alsfrs": [14], "boston": [14], "nmj": [14], "ela": [14], "trach": [14], "use": [14], "range": [14], "dx": [14], "stoma": [14], "mic-key": [14], "neurologic": [14], "tracheotomy": [14], "always": [14], "percutaneous": [14], "avaps": [14], "motion": [14], "type": [14, 16], "amyotrophic lateral sclerosis functional rating scale": [14], "uk": [14], "veteran": [14], "average": [14], "patient's blood": [14], "lp": [14], "patient's body": [14], "rt": [14], "oxygen": [14], "neuron": [14, 16], "s": [14], "cals/cals": [14], "center": [14], "spo2": [14], "commonly": [14], "assured pressure support": [14], "abbreviation": [14], "revised": [14], "trache": [14], "measurement": [14], "real": [15], "constipation": [15], "spinal": [16], "adult": [16], "-pbp": [16], "pbp": [16], "correct terminology": [16], "lmns": [16], "example": [16], "yes": [16], "bulbar": [16], "-als": [16], "store": [16], "-sma": [16], "above diseases": [16], "term": [16], "-pma": [16], "sma": [16], "umn and lmn": [16], "umns": [16], "only umn": [16], "no umn": [16], "obviously": [16], "must": [16], "doe": [16], "words": [16], "sbma": [16], "mind's": [16], "-pls": [16], "consider": [16], "kennedy": [16], "bulbar muscular atrophy": [16], "involvement": [16], "progressive muscular atrophy": [16], "way": [16], "left arm": [16], "dubowitz-disease": [16], "primarily": [16], "only lmn": [16], "incorrect": [16], "pma": [16], "this is not how upper and lower motor neurons work": [16], "umn/lmn": [16], "no lmn": [16], "nerves": [16], "and/or": [16], "spinal muscular atrophy": [16], "pls": [16], "github": [17], "downloading": [17], "explanation": [17], "editor": [17]}